CHANGELOG.md
LICENSE
README.md
fastapi_limiterx/__init__.py
fastapi_limiterx/depends.py
fastapi_limiterx/main.py
fastapi_limiterx-0.1.6.dist-info/LICENSE
fastapi_limiterx-0.1.6.dist-info/WHEEL
fastapi_limiterx-0.1.6.dist-info/METADATA
fastapi_limiterx-0.1.6.dist-info/RECORD
