Metadata-Version: 2.1
Name: fastapi-limiterx
Version: 0.1.6
Summary: A request rate limiter for fastapi
Home-page: https://github.com/long2ice/fastapi-limiter
License: Apache2.0
Keywords: fastapi,limiter
Author: long2ice
Author-email: long2ice@gmail.com
Requires-Python: >=3.7,<4.0
Classifier: License :: Other/Proprietary License
Classifier: Programming Language :: Python :: 3
Classifier: Programming Language :: Python :: 3.10
Classifier: Programming Language :: Python :: 3.7
Classifier: Programming Language :: Python :: 3.8
Classifier: Programming Language :: Python :: 3.9
Requires-Dist: fastapi
Requires-Dist: redis
Project-URL: Documentation, https://github.com/long2ice/fastapi-limiter
Project-URL: Repository, https://github.com/milisp/fastapi-limiterx.git
